{
	"animations": [
		{
			"loop": true,
			"offsets": [
				0,
				0
			],
			"anim": "idle",
			"fps": 24,
			"name": "IDLE",
			"indices": []
		},
		{
			"loop": false,
			"offsets": [
				10,
				50
			],
			"anim": "singUP",
			"fps": 24,
			"name": "UP",
			"indices": []
		},
		{
			"loop": false,
			"offsets": [
				80,
				20
			],
			"anim": "singLEFT",
			"fps": 24,
			"name": "LEFT",
			"indices": []
		},
		{
			"loop": false,
			"offsets": [
				-10,
				-30
			],
			"anim": "singRIGHT",
			"fps": 24,
			"name": "RIGHT",
			"indices": []
		},
		{
			"loop": false,
			"offsets": [
				50,
				-34
			],
			"anim": "singDOWN",
			"fps": 24,
			"name": "DOWN",
			"indices": []
		}
	],
	"no_antialiasing": false,
	"image": "characters/bambi-rage",
	"position": [
		-5,
		350
	],
	"healthicon": "bambiRage",
	"flip_x": false,
	"healthbar_colors": [
		255,
		0,
		0
	],
	"camera_position": [
		-10,
		67
	],
	"sing_duration": 6.1,
	"scale": 1.3
}